machinelearning/__init__.py
machinelearning/metrics.py
machinelearning/randomforest.py
machinelearning/optimization/__init__.py
machinelearning/optimization/genetic_algorithm.py
machinelearning/stats/__init__.py
machinelearning/stats/pandas/__init__.py
machinelearning/stats/pandas/statistics_calculator.py
machinelearning/stats/spark/__init__.py
machinelearning/stats/spark/statistics_calculator.py
machinelearning/tree/__init__.py
machinelearning/tree/decision_tree.py
machinelearning/tree/general_tree.py
machinelearning/tree/node/__init__.py
machinelearning/tree/node/branch.py
machinelearning/tree/node/internalnode.py
machinelearning/tree/node/treenode.py
random_genetic_forest-0.0a2.dist-info/DESCRIPTION.rst
random_genetic_forest-0.0a2.dist-info/METADATA
random_genetic_forest-0.0a2.dist-info/RECORD
random_genetic_forest-0.0a2.dist-info/WHEEL
random_genetic_forest-0.0a2.dist-info/metadata.json
random_genetic_forest-0.0a2.dist-info/top_level.txt
tests/__init__.py
tests/test_randomforest.py
tests/optimization/__init__.py
tests/optimization/test_genetic_algorithm.py
tests/stats/__init__.py
tests/stats/pandas/__init__.py
tests/stats/pandas/test_stats_calculator.py
tests/stats/spark/__init__.py
tests/stats/spark/test_statistics_calculator.py
tests/tree/__init__.py
tests/tree/test_descisiontree.py
tests/tree/test_generaltree.py
