Metadata-Version: 2.0
Name: random-genetic-forest
Version: 0.0a2
Summary: This is a machine learning package that includes a theoretical optimized variation of the random forest learning algorithm.
Home-page: https://github.com/tab-dev/Random-Genetic-Forest
Author: Timothy Bennett
Author-email: tabdevelopment1@gmail.com
License: UNKNOWN
Platform: UNKNOWN
Classifier: Programming Language :: Python :: 3
Classifier: License :: OSI Approved :: MIT License
Classifier: Operating System :: OS Independent
Requires-Python: >=3.6.7
